ancient/NotoSansCuneiform-Regular.ttf
ancient/__init__.py
ancient/ai_chat.py
ancient/animate.py
ancient/background.jpg
ancient/core.py
ancient/mappings.py
ancient/releases.py
ancient/reverse_ancient_converter.py
ancient/timeline.py
ancient/visualizer.py
ancient/web_app.py
ancient/static/script.js
ancient/static/service-worker.js
ancient/static/styles.css
ancient/static/icons/icon-144x144.png
ancient/static/icons/icon-192x192.png
ancient/static/icons/icon-384x384.png
ancient/static/icons/icon-48x48.png
ancient/static/icons/icon-512x512.png
ancient/static/icons/icon-72x72.png
ancient/static/icons/icon-96x96.png
ancient/static/icons/icon128.png
ancient/static/icons/icon48.png
ancient/templates/index.html
ancientlinesoftheworld-4.0.0.dist-info/METADATA
ancientlinesoftheworld-4.0.0.dist-info/WHEEL
ancientlinesoftheworld-4.0.0.dist-info/entry_points.txt
ancientlinesoftheworld-4.0.0.dist-info/top_level.txt
ancientlinesoftheworld-4.0.0.dist-info/RECORD
