Metadata-Version: 2.4
Name: ancientlinesoftheworld
Version: 4.0.0
Summary: Convert Persian and English text to ancient scripts like Pahlavi, Avestan, Cuneiform, and Manichaean.
Home-page: https://github.com/amirhossinpython/ancientlinesoftheworld-
Author: Amir Hossein Khazaei
Author-email: amirhossinpython03@gmail.com
License: MIT
Requires-Python: >=3.8
Requires-Dist: deep-translator
Requires-Dist: Pillow
Requires-Dist: openai
Requires-Dist: feedparser
Requires-Dist: Flask
Dynamic: author
Dynamic: author-email
Dynamic: description
Dynamic: description-content-type
Dynamic: home-page
Dynamic: license
Dynamic: requires-dist
Dynamic: requires-python
Dynamic: summary
